stactools/modis/__init__.py
stactools/modis/cog.py
stactools/modis/commands.py
stactools/modis/constants.py
stactools/modis/file.py
stactools/modis/metadata.py
stactools/modis/product.py
stactools/modis/stac.py
stactools/modis/utils.py
stactools/modis/warnings.py
stactools/modis/fragments/__init__.py
stactools/modis/fragments/09A1/061/bands.json
stactools/modis/fragments/09A1/061/collection.json
stactools/modis/fragments/09A1/061/item.json
stactools/modis/fragments/09Q1/061/bands.json
stactools/modis/fragments/09Q1/061/collection.json
stactools/modis/fragments/09Q1/061/item.json
stactools/modis/fragments/10A1/006/bands.json
stactools/modis/fragments/10A1/006/collection.json
stactools/modis/fragments/10A1/006/item.json
stactools/modis/fragments/10A1/061/bands.json
stactools/modis/fragments/10A1/061/collection.json
stactools/modis/fragments/10A1/061/item.json
stactools/modis/fragments/10A2/061/bands.json
stactools/modis/fragments/10A2/061/collection.json
stactools/modis/fragments/10A2/061/item.json
stactools/modis/fragments/11A1/006/bands.json
stactools/modis/fragments/11A1/006/collection.json
stactools/modis/fragments/11A1/006/item.json
stactools/modis/fragments/11A1/061/bands.json
stactools/modis/fragments/11A1/061/collection.json
stactools/modis/fragments/11A1/061/item.json
stactools/modis/fragments/11A2/006/bands.json
stactools/modis/fragments/11A2/006/collection.json
stactools/modis/fragments/11A2/006/item.json
stactools/modis/fragments/11A2/061/bands.json
stactools/modis/fragments/11A2/061/collection.json
stactools/modis/fragments/11A2/061/item.json
stactools/modis/fragments/12Q1/006/bands.json
stactools/modis/fragments/12Q1/006/collection.json
stactools/modis/fragments/12Q1/006/item.json
stactools/modis/fragments/13A1/006/bands.json
stactools/modis/fragments/13A1/006/collection.json
stactools/modis/fragments/13A1/006/item.json
stactools/modis/fragments/13A1/061/bands.json
stactools/modis/fragments/13A1/061/collection.json
stactools_modis-0.2.0.dist-info/LICENSE
stactools_modis-0.2.0.dist-info/METADATA
stactools_modis-0.2.0.dist-info/WHEEL
stactools_modis-0.2.0.dist-info/top_level.txt
stactools_modis-0.2.0.dist-info/RECORD
