Metadata-Version: 2.1
Name: stactools-modis
Version: 0.2.0
Summary: stactools package for MODIS data
Home-page: https://github.com/stactools-modis/stactools-modis
Author: Pete Gadomski
Author-email: pete.gadomski@gmail.com
License: UNKNOWN
Project-URL: Documentation, https://stactools-modis.readthedocs.io/en/latest/
Project-URL: Issues, https://github.com/stactools-modis/stactools-modis/issues
Keywords: stactools,pystac,catalog,STAC,MODIS
Platform: UNKNOWN
Classifier: Development Status :: 4 - Beta
Classifier: License :: OSI Approved :: Apache Software License
Classifier: Programming Language :: Python :: 3.7
Classifier: Programming Language :: Python :: 3.8
Classifier: Programming Language :: Python :: 3.9
License-File: LICENSE
Requires-Dist: stactools (>=0.3.0)
Requires-Dist: click (!=8.1.0)
